qref/__init__.py
qref/experimental/__init__.py
qref/experimental/rendering.py
qref/functools.py
qref/py.typed
qref/schema_v1.py
qref/verification.py
qref-0.11.0.dist-info/LICENSE
qref-0.11.0.dist-info/METADATA
qref-0.11.0.dist-info/WHEEL
qref-0.11.0.dist-info/entry_points.txt
qref-0.11.0.dist-info/RECORD
