Metadata-Version: 2.1
Name: qref
Version: 0.11.0
Summary: Quantum Resource Estimation Format
License: Apache 2.0
Author: PsiQuantum, Corp.
Requires-Python: >=3.10,<4.0
Classifier: License :: Other/Proprietary License
Classifier: Programming Language :: Python :: 3
Classifier: Programming Language :: Python :: 3.10
Classifier: Programming Language :: Python :: 3.11
Classifier: Programming Language :: Python :: 3.12
Requires-Dist: graphviz (>=0.20.3,<0.21.0)
Requires-Dist: pydantic (>=2.0,<3.0)
